touchdown/__init__.py
touchdown/template.py
touchdown/aws/__init__.py
touchdown/aws/account.py
touchdown/aws/common.py
touchdown/aws/external_account.py
touchdown/aws/password_policy.py
touchdown/aws/replacement.py
touchdown/aws/session.py
touchdown/aws/acm/__init__.py
touchdown/aws/acm/certificate.py
touchdown/aws/apigateway/__init__.py
touchdown/aws/apigateway/deployment.py
touchdown/aws/apigateway/integration.py
touchdown/aws/apigateway/integration_response.py
touchdown/aws/apigateway/method.py
touchdown/aws/apigateway/method_response.py
touchdown/aws/apigateway/model.py
touchdown/aws/apigateway/resource.py
touchdown/aws/apigateway/rest_api.py
touchdown/aws/apigateway/stage.py
touchdown/aws/cloudfront/__init__.py
touchdown/aws/cloudfront/common.py
touchdown/aws/cloudfront/distribution.py
touchdown/aws/cloudfront/streaming_distribution.py
touchdown/aws/cloudfront/tail.py
touchdown/aws/cloudtrail/__init__.py
touchdown/aws/cloudtrail/trail.py
touchdown/aws/cloudwatch/__init__.py
touchdown/aws/cloudwatch/alarm.py
touchdown/aws/cloudwatch/metric.py
touchdown/aws/data/_retry.json
touchdown/aws/data/acm/2015-12-08/waiters-2.json
touchdown/aws/data/cloudfront/2016-01-28/waiters-2.json
touchdown/aws/data/ec2/2015-10-01/waiters-2.json
touchdown/aws/data/iam/2010-05-08/waiters-2.json
touchdown/aws/ec2/__init__.py
touchdown/aws/ec2/ami.py
touchdown/aws/ec2/ami_copy.py
touchdown/aws/ec2/auto_scaling_group.py
touchdown/aws/ec2/auto_scaling_policy.py
touchdown/aws/ec2/instance.py
touchdown/aws/ec2/keypair.py
touchdown/aws/ec2/launch_configuration.py
touchdown/aws/ec2/volume.py
touchdown/aws/ec2/volume_attachment.py
touchdown/aws/elasticache/__init__.py
touchdown/aws/elasticache/cache.py
touchdown/aws/elasticache/replication_group.py
touchdown/aws/elasticache/subnet_group.py
touchdown/aws/elastictranscoder/__init__.py
touchdown/aws/elastictranscoder/pipeline.py
touchdown/aws/elb/__init__.py
touchdown/aws/elb/load_balancer.py
touchdown/aws/events/__init__.py
touchdown-0.15.16.dist-info/LICENSE
touchdown-0.15.16.dist-info/METADATA
touchdown-0.15.16.dist-info/WHEEL
touchdown-0.15.16.dist-info/entry_points.txt
touchdown-0.15.16.dist-info/top_level.txt
touchdown-0.15.16.dist-info/RECORD
