Metadata-Version: 2.1
Name: touchdown
Version: 0.15.16
Summary: Orchestration and configuration management in Python
Home-page: http://yaybu.com/
Author: Isotoma Limited
Author-email: support@isotoma.com
License: Apache Software License
Platform: UNKNOWN
Classifier: Intended Audience :: System Administrators
Classifier: Operating System :: POSIX
Classifier: License :: OSI Approved :: Apache Software License
Classifier: Programming Language :: Python :: 2
Classifier: Programming Language :: Python :: 2.7
Classifier: Programming Language :: Python :: 3
Classifier: Programming Language :: Python :: 3.3
Classifier: Programming Language :: Python :: 3.4
Classifier: Programming Language :: Python :: 3.5
Classifier: Programming Language :: Python :: Implementation :: CPython
Classifier: Programming Language :: Python :: Implementation :: PyPy
Requires-Dist: six
Requires-Dist: contextlib2
Requires-Dist: netaddr
Requires-Dist: fuselage (>=1.0.0)
Requires-Dist: botocore (>=1.4.28)
Requires-Dist: requests
Requires-Dist: python-gnupg
